hic2cool/__init__.py
hic2cool/__main__.py
hic2cool/_version.py
hic2cool/hic2cool_config.py
hic2cool/hic2cool_updates.py
hic2cool/hic2cool_utils.py
hic2cool-1.0.0.dist-info/LICENSE.txt
hic2cool-1.0.0.dist-info/METADATA
hic2cool-1.0.0.dist-info/WHEEL
hic2cool-1.0.0.dist-info/RECORD
