Metadata-Version: 2.1
Name: hic2cool
Version: 1.0.0
Summary: Converter between hic files (from juicer) and single-resolution or multi-resolution cool files (for cooler).  Both hic and cool files describe Hi-C contact matrices. Intended to be lightweight, this can be used as an imported package or a stand-alone Python tool for command line conversion.
Home-page: https://github.com/4dn-dcic/hic2cool/
License: MIT
Keywords: bioinformatics,genomics,hi-c,juicer,cooler,contact-matrix,file-format
Author: Carl Vitzthum
Author-email: carl.vitzthum@gmail.com
Requires-Python: >=3.8,<3.10
Classifier: Development Status :: 4 - Beta
Classifier: Intended Audience :: Developers
Classifier: Intended Audience :: Science/Research
Classifier: License :: OSI Approved :: MIT License
Classifier: Operating System :: OS Independent
Classifier: Programming Language :: Python :: 3
Classifier: Programming Language :: Python :: 3.8
Classifier: Programming Language :: Python :: 3.9
Classifier: Topic :: Scientific/Engineering :: Bio-Informatics
Classifier: Topic :: Software Development :: Libraries :: Python Modules
Requires-Dist: cooler (==0.9.3)
Requires-Dist: h5py (>=2.5.0)
Requires-Dist: numpy (>=1.9)
Requires-Dist: pandas (>=1.0)
Requires-Dist: scipy (>=1.10.1)
Project-URL: Repository, https://github.com/4dn-dcic/hic2cool/
